LICENSE
README.md
hil_testbench/__init__.py
hil_testbench/health_monitor.py
hil_testbench/offline_bundle.py
hil_testbench/api/__init__.py
hil_testbench/api/command.py
hil_testbench/api/extras.py
hil_testbench/api/parser.py
hil_testbench/api/rq6
hil_testbench/api/schema.py
hil_testbench/api/task.py
hil_testbench/api/thresholds.py
hil_testbench/cli/__init__.py
hil_testbench/cli/commands.py
hil_testbench/cli/config_loader.py
hil_testbench/cli/config_template.py
hil_testbench/cli/constants.py
hil_testbench/cli/describe.py
hil_testbench/cli/executor.py
hil_testbench/cli/monitor.py
hil_testbench/cli/parser.py
hil_testbench/cli/prune_logs.py
hil_testbench/cli/run_summary.py
hil_testbench/cli/shutdown.py
hil_testbench/cli/task_builder.py
hil_testbench/cli/task_listing.py
hil_testbench/cli/task_loader.py
hil_testbench/cli/task_utils.py
hil_testbench/cli/utils.py
hil_testbench/config/config_loader.py
hil_testbench/config/config_merger.py
hil_testbench/config/run_config.py
hil_testbench/config/task_config.py
hil_testbench/config/prod/tasks.prod.yaml
hil_testbench/data_processing/accumulators.py
hil_testbench/data_processing/derived_metrics.py
hil_testbench/data_processing/derived_processor.py
hil_testbench/data_processing/events.py
hil_testbench/data_processing/expression_engine.py
hil_testbench/data_processing/extractors.py
hil_testbench/data_processing/parsers.py
hil_testbench/data_processing/pipeline.py
hil_testbench/data_processing/schema_parser.py
hil_testbench/data_processing/status_evaluator.py
hil_testbench/data_processing/writers.py
hil_testbench/data_structs/hosts.py
hil_testbench/data_structs/parameters.py
hil_testbench/data_structs/threshold_utils.py
hil_testbench/display/live_display.py
hil_testbench/display/sections.py
hil_testbench/display/sparkline.py
hil_testbench/display/threshold_evaluator.py
hil_testbench/internal/plugin_adapter.py
hil_testbench/run/__init__.py
hil_testbench/run/exceptions.py
hil_testbench/run/graph_executor.py
hil_testbench-0.1.3.dist-info/METADATA
hil_testbench-0.1.3.dist-info/WHEEL
hil_testbench-0.1.3.dist-info/entry_points.txt
hil_testbench-0.1.3.dist-info/licenses/LICENSE
hil_testbench-0.1.3.dist-info/RECORD
