Metadata-Version: 2.4
Name: hil-testbench
Version: 0.1.3
Summary: Hardware-in-Loop testbench framework with concurrent task execution, structured logging, and live metrics.
Author-email: HIL Testbench Contributors <noreply@example.com>
Maintainer-email: HIL Testbench Maintainers <noreply@example.com>
License-Expression: MIT
License-File: LICENSE
Keywords: automation,concurrent,hardware-in-loop,hil,monitoring,ssh,tasks,testbench
Classifier: Development Status :: 3 - Alpha
Classifier: Intended Audience :: Developers
Classifier: Programming Language :: Python :: 3
Classifier: Programming Language :: Python :: 3.9
Classifier: Programming Language :: Python :: 3.10
Classifier: Programming Language :: Python :: 3.11
Requires-Python: >=3.9
Requires-Dist: networkx>=3.0
Requires-Dist: paramiko>=3.0.0
Requires-Dist: pint>=0.22
Requires-Dist: psutil>=5.9.0
Requires-Dist: pywinpty>=2.0.0; sys_platform == 'win32'
Requires-Dist: pyyaml>=6.0.0
Requires-Dist: rich>=13.0.0
Requires-Dist: simpleeval>=0.9.13
Provides-Extra: dev
Requires-Dist: hypothesis>=6.92.0; extra == 'dev'
Requires-Dist: matplotlib>=3.8.0; extra == 'dev'
Requires-Dist: numpy>=1.26.0; extra == 'dev'
Requires-Dist: pycg>=0.0.8; extra == 'dev'
Requires-Dist: pytest-cov>=4.1.0; extra == 'dev'
Requires-Dist: pytest-mock>=3.12.0; extra == 'dev'
Requires-Dist: pytest>=7.4.0; extra == 'dev'
Requires-Dist: ruff>=0.1.0; extra == 'dev'
Requires-Dist: simpleeval>=0.9.10; extra == 'dev'
Requires-Dist: tox>=4.0.0; extra == 'dev'
Provides-Extra: maintainer
Requires-Dist: build>=1.0.0; extra == 'maintainer'
Requires-Dist: detect-secrets>=1.5.0; extra == 'maintainer'
Requires-Dist: interrogate>=1.7.0; extra == 'maintainer'
Requires-Dist: pre-commit>=3.5.0; extra == 'maintainer'
Requires-Dist: pytest-testmon>=2.1.0; extra == 'maintainer'
Requires-Dist: twine>=4.0.0; extra == 'maintainer'
